{
  "MyRouter.js": "1448350017000",
  "css/style.css": "1448350017000",
  "dev/devapp.js": "1452145486000",
  "dev/devlogon.js": "1452145331000",
  "i18n/messageBundle.properties": "1448350017000",
  "util/Controller.js": "1448350017000",
  "util/Formatter.js": "1448350017000",
  "view/App.view.xml": "1448350017000",
  "view/Detail.controller.js": "1448350017000",
  "view/Detail.view.xml": "1448350017000",
  "view/DetailInfoForm.fragment.xml": "1448350017000",
  "view/Master.controller.js": "1452145427000",
  "view/Master.view.xml": "1448350017000",
  "view/NotFound.view.xml": "1448350017000",
  "Component.js": "1448350017000",
  "index.html": "1448350017000",
  "model/metadata.xml": "1448350021000",
  "preview_hidden.html": "1448350042000"
}